web3_reactor/__init__.py
web3_reactor/cmd_tools/__init__.py
web3_reactor/cmd_tools/init_helper.py
web3_reactor/core/__init__.py
web3_reactor/core/channel.py
web3_reactor/core/context.py
web3_reactor/core/dispatcher.py
web3_reactor/core/errors.py
web3_reactor/core/events.py
web3_reactor/core/plugin.py
web3_reactor/exports.py
web3_reactor/services/UUID.py
web3_reactor/services/_configer.py
web3_reactor/services/config.py
web3_reactor/services/lock.py
web3_reactor/services/logger.py
web3_reactor/services/utils.py
web3_reactor/services/web3/eth/__init__.py
web3_reactor/services/web3/eth/account.py
web3_reactor/services/web3/eth/gas_tracker.py
web3_reactor/services/web3/eth/w3.py
web3_reactor/types/__init__.py
web3_reactor/types/broadcast_actions.py
web3_reactor-0.1.0.dist-info/LICENSE
web3_reactor-0.1.0.dist-info/METADATA
web3_reactor-0.1.0.dist-info/WHEEL
web3_reactor-0.1.0.dist-info/RECORD
