Metadata-Version: 2.1
Name: web3-reactor
Version: 0.1.0
Summary: A blockchain event processing suite based on python asyncio
License: MIT
Author: majoson-chen
Requires-Python: >=3.9,<4.0
Classifier: License :: OSI Approved :: MIT License
Classifier: Programming Language :: Python :: 3
Classifier: Programming Language :: Python :: 3.9
Classifier: Programming Language :: Python :: 3.10
Classifier: Programming Language :: Python :: 3.11
Requires-Dist: click (>=8.1.6,<9.0.0)
Requires-Dist: httpx (>=0.24.1,<0.25.0)
Requires-Dist: loguru (>=0.7.0,<0.8.0)
Requires-Dist: pyyaml (>=6.0.1,<7.0.0)
Requires-Dist: web3 (>=6.8.0,<7.0.0)
Requires-Dist: werkzeug (>=2.3.6,<3.0.0)
